frontend/__init__.py
frontend/eeg_eventview.py
frontend/turtlewave_gui.py
turtlewave_hdEEG/__init__.py
turtlewave_hdEEG/addjson2xml.py
turtlewave_hdEEG/annotation.py
turtlewave_hdEEG/dataset.py
turtlewave_hdEEG/eventprocessor.py
turtlewave_hdEEG/extensions.py
turtlewave_hdEEG/json_to_annotations.py
turtlewave_hdEEG/pacprocessor.py
turtlewave_hdEEG/swprocessor.py
turtlewave_hdEEG/utils.py
turtlewave_hdEEG/visualization.py
turtlewave_hdeeg-2.1.0.dist-info/METADATA
turtlewave_hdeeg-2.1.0.dist-info/WHEEL
turtlewave_hdeeg-2.1.0.dist-info/entry_points.txt
turtlewave_hdeeg-2.1.0.dist-info/top_level.txt
turtlewave_hdeeg-2.1.0.dist-info/RECORD
